lingualabpy/__init__.py
lingualabpy/_version.py
lingualabpy/io.py
lingualabpy/plot.py
lingualabpy/audio/__init__.py
lingualabpy/audio/metrics.py
lingualabpy/audio/triming.py
lingualabpy/cli/__init__.py
lingualabpy/cli/audio_metrics.py
lingualabpy/cli/audio_triming.py
lingualabpy/cli/docx2json.py
lingualabpy/cli/jsons2csv.py
lingualabpy/cli/plot_sound.py
lingualabpy/neuroimaging/__init__.py
lingualabpy/neuroimaging/hcp_connectome.py
lingualabpy/text/__init__.py
lingualabpy/text/parser.py
lingualabpy/text/textgrid.py
lingualabpy/tools/__init__.py
lingualabpy/tools/data.py
lingualabpy/tools/interval.py
lingualabpy-0.1.1.dist-info/METADATA
lingualabpy-0.1.1.dist-info/WHEEL
lingualabpy-0.1.1.dist-info/entry_points.txt
lingualabpy-0.1.1.dist-info/licenses/LICENSE
lingualabpy-0.1.1.dist-info/RECORD
