Metadata-Version: 2.4
Name: lingualabpy
Version: 0.1.1
Summary: Tools and utilities from the LINGUA laboratory
Project-URL: Documentation, https://github.com/lingualab/lingualabpy
Project-URL: Source, https://github.com/lingualab/lingualabpy
Project-URL: Tracker, https://github.com/lingualab/lingualabpy/issues
Author-email: Christophe Bedetti <christophe.bedetti@umontreal.ca>
License: MIT License
License-File: LICENSE
Classifier: Development Status :: 3 - Alpha
Classifier: Intended Audience :: Developers
Classifier: Intended Audience :: Science/Research
Classifier: License :: OSI Approved :: MIT License
Classifier: Operating System :: MacOS :: MacOS X
Classifier: Operating System :: Microsoft :: Windows
Classifier: Operating System :: POSIX :: Linux
Classifier: Programming Language :: Python :: 3 :: Only
Classifier: Programming Language :: Python :: 3.8
Classifier: Programming Language :: Python :: 3.9
Classifier: Programming Language :: Python :: 3.10
Classifier: Programming Language :: Python :: 3.11
Classifier: Topic :: Scientific/Engineering
Requires-Python: >=3.8.1
Requires-Dist: click
Requires-Dist: matplotlib
Requires-Dist: nilearn==0.12.1
Requires-Dist: opencv-python
Requires-Dist: pandas
Requires-Dist: praat-parselmouth
Requires-Dist: praat-textgrids
Requires-Dist: pydub
Requires-Dist: python-docx
Provides-Extra: style
Requires-Dist: black; extra == 'style'
Requires-Dist: ruff; extra == 'style'
Provides-Extra: test
Requires-Dist: pytest; extra == 'test'
Requires-Dist: pytest-cov; extra == 'test'
